{"packages":{"selene\/writer":{"dev-development":{"name":"selene\/writer","description":"Helper component for generating source code","keywords":["text","string","writer","source-code"],"homepage":"","version":"dev-development","version_normalized":"dev-development","license":["MIT"],"authors":[{"name":"Thomas Appel","email":"mail@thomas-appel.com"}],"source":{"type":"git","url":"https:\/\/github.com\/seleneapp\/writer.git","reference":"74827370c9bbce01503693b19a315ca8b5777553"},"dist":{"type":"zip","url":"https:\/\/api.github.com\/repos\/seleneapp\/writer\/zipball\/74827370c9bbce01503693b19a315ca8b5777553","reference":"74827370c9bbce01503693b19a315ca8b5777553","shasum":""},"type":"library","time":"2014-08-19T03:25:19+00:00","autoload":{"psr-4":{"Selene\\Module\\Writer\\":""}},"require":{"selene\/common":"dev-development"},"require-dev":{"league\/phpunit-coverage-listener":"dev-master","selene\/testsuite":"dev-development"},"uid":218146}}}}