{"packages":{"ampluso\/eel-monitor":{"dev-master":{"name":"ampluso\/eel-monitor","description":"Simple Web Server monitoring","keywords":["web","monitoring","server","service"],"homepage":"http:\/\/eel-monitor.ampluso.com\/","version":"dev-master","version_normalized":"9999999-dev","license":["MIT"],"authors":[{"name":"Marcin Chylek","email":"marcin@chylek.pl","homepage":"http:\/\/chylek.pl"},{"name":"AMPLUSO","email":"bok@ampluso.pl","homepage":"http:\/\/ampluso.pl"}],"source":{"type":"git","url":"https:\/\/github.com\/eel-monitor\/eel-monitor.git","reference":"86f2a8b7490bcfeef8741e25ab4f2feba1d07f0e"},"dist":{"type":"zip","url":"https:\/\/api.github.com\/repos\/eel-monitor\/eel-monitor\/zipball\/86f2a8b7490bcfeef8741e25ab4f2feba1d07f0e","reference":"86f2a8b7490bcfeef8741e25ab4f2feba1d07f0e","shasum":""},"type":"library","time":"2013-01-02T14:27:01+00:00","autoload":{"psr-0":{"EelMonitor":"src\/"}},"bin":["bin\/eel-monitor"],"require":{"php":">=5.3.0","symfony\/console":"2.1.*","symfony\/finder":"2.1.*","symfony\/process":"2.1.*","symfony\/yaml":"2.1.*","symfony\/http-foundation":"2.1.*"},"uid":10287}}}}