{"packages":{"b2r\/php-undefined":{"dev-master":{"name":"b2r\/php-undefined","description":"PHP Undefined Singleton","keywords":[],"homepage":"","version":"dev-master","version_normalized":"9999999-dev","license":["MIT"],"authors":[{"name":"b2r","email":"b2r.info@gmail.com"}],"source":{"type":"git","url":"https:\/\/github.com\/b2r\/php-undefined.git","reference":"36de96bff9f756b9a07dc89e24d77f277e50fb5f"},"dist":{"type":"zip","url":"https:\/\/api.github.com\/repos\/b2r\/php-undefined\/zipball\/36de96bff9f756b9a07dc89e24d77f277e50fb5f","reference":"36de96bff9f756b9a07dc89e24d77f277e50fb5f","shasum":""},"type":"library","time":"2013-12-11T02:50:42+00:00","autoload":{"psr-0":{"b2r\\":"src\/"}},"require":{"php":">=5.4"},"uid":107298},"v0.1.0":{"name":"b2r\/php-undefined","description":"PHP Undefined Singleton","keywords":[],"homepage":"","version":"v0.1.0","version_normalized":"0.1.0.0","license":["MIT"],"authors":[{"name":"b2r","email":"b2r.info@gmail.com"}],"source":{"type":"git","url":"https:\/\/github.com\/b2r\/php-undefined.git","reference":"5955485c13cf3313d89a50f1b0e078a81e29c312"},"dist":{"type":"zip","url":"https:\/\/api.github.com\/repos\/b2r\/php-undefined\/zipball\/5955485c13cf3313d89a50f1b0e078a81e29c312","reference":"5955485c13cf3313d89a50f1b0e078a81e29c312","shasum":""},"type":"library","time":"2013-12-05T07:52:42+00:00","autoload":{"psr-0":{"b2r\\":"src\/"}},"require":{"php":">=5.4"},"uid":107297}}}}