{"packages":{"irestful\/concreteauthentificationtokens":{"13.11.28":{"name":"irestful\/concreteauthentificationtokens","description":"","keywords":[],"homepage":"https:\/\/github.com\/irestful\/ConcreteAuthentificationTokens","version":"13.11.28","version_normalized":"13.11.28.0","license":["MIT"],"authors":[{"name":"Steve Rodrigue","email":"steve@irestful.com"}],"source":{"type":"git","url":"https:\/\/github.com\/irestful\/ConcreteAuthentificationTokens.git","reference":"8012d66853c9d238deadb19acb1d8ef9f9a2b1a0"},"dist":{"type":"zip","url":"https:\/\/api.github.com\/repos\/irestful\/ConcreteAuthentificationTokens\/zipball\/8012d66853c9d238deadb19acb1d8ef9f9a2b1a0","reference":"8012d66853c9d238deadb19acb1d8ef9f9a2b1a0","shasum":""},"type":"library","time":"2015-01-20T09:41:59+00:00","autoload":{"psr-0":{"ConcreteAuthentificationTokens":"."}},"require":{"php":">=5.4.0","irestful\/concretefunctionaltesthelpers":"13.11.28","irestful\/authentificationtokens":"13.11.28","irestful\/jsons":"13.11.28","irestful\/concretedependencyinjectionobjectplaceholders":"13.11.28","irestful\/concretebooleans":"13.11.28","irestful\/concretejsons":"13.11.28","irestful\/concreteauthentifications":"13.11.28"},"require-dev":{"phpunit\/phpunit":"3.7.*"},"uid":156591},"dev-master":{"name":"irestful\/concreteauthentificationtokens","description":"","keywords":[],"homepage":"https:\/\/github.com\/irestful\/ConcreteAuthentificationTokens","version":"dev-master","version_normalized":"9999999-dev","license":["MIT"],"authors":[{"name":"Steve Rodrigue","email":"steve@irestful.com"}],"source":{"type":"git","url":"https:\/\/github.com\/irestful\/ConcreteAuthentificationTokens.git","reference":"8012d66853c9d238deadb19acb1d8ef9f9a2b1a0"},"dist":{"type":"zip","url":"https:\/\/api.github.com\/repos\/irestful\/ConcreteAuthentificationTokens\/zipball\/8012d66853c9d238deadb19acb1d8ef9f9a2b1a0","reference":"8012d66853c9d238deadb19acb1d8ef9f9a2b1a0","shasum":""},"type":"library","time":"2015-01-20T09:41:59+00:00","autoload":{"psr-0":{"ConcreteAuthentificationTokens":"."}},"require":{"php":">=5.4.0","irestful\/concretefunctionaltesthelpers":"13.11.28","irestful\/authentificationtokens":"13.11.28","irestful\/jsons":"13.11.28","irestful\/concretedependencyinjectionobjectplaceholders":"13.11.28","irestful\/concretebooleans":"13.11.28","irestful\/concretejsons":"13.11.28","irestful\/concreteauthentifications":"13.11.28"},"require-dev":{"phpunit\/phpunit":"3.7.*"},"uid":156592}}}}