{"packages":{"ovimihai\/react-amqp":{"dev-master":{"name":"ovimihai\/react-amqp","description":"AMQP bindings for ReactPHP","keywords":["rabbitmq","AMQP"],"homepage":"","version":"dev-master","version_normalized":"9999999-dev","license":["MIT"],"authors":[{"name":"Jeremy Cook","email":"jeremycook0@gmail.com"}],"source":{"type":"git","url":"https:\/\/github.com\/ovimihai\/ReactAMQP.git","reference":"2b957e2f2f3686452a1d31c6b3b0f7bcc4b8bf3d"},"dist":{"type":"zip","url":"https:\/\/api.github.com\/repos\/ovimihai\/ReactAMQP\/zipball\/2b957e2f2f3686452a1d31c6b3b0f7bcc4b8bf3d","reference":"2b957e2f2f3686452a1d31c6b3b0f7bcc4b8bf3d","shasum":""},"type":"library","time":"2015-07-30T12:43:50+00:00","autoload":{"psr-0":{"JCook\\ReactAMQP":"src"}},"require":{"php":">=5.3.0","ext-amqp":"*","evenement\/evenement":"1.0.*","react\/event-loop":"0.3.*"},"uid":476400},"dev-pull_request":{"name":"ovimihai\/react-amqp","description":"AMQP bindings for ReactPHP","keywords":["rabbitmq","AMQP"],"homepage":"","version":"dev-pull_request","version_normalized":"dev-pull_request","license":["MIT"],"authors":[{"name":"Jeremy Cook","email":"jeremycook0@gmail.com"}],"source":{"type":"git","url":"https:\/\/github.com\/ovimihai\/ReactAMQP.git","reference":"5cf79fa5f632bda13ea30372fd959b62535676ed"},"dist":{"type":"zip","url":"https:\/\/api.github.com\/repos\/ovimihai\/ReactAMQP\/zipball\/5cf79fa5f632bda13ea30372fd959b62535676ed","reference":"5cf79fa5f632bda13ea30372fd959b62535676ed","shasum":""},"type":"library","time":"2015-07-30T12:45:28+00:00","autoload":{"psr-0":{"JCook\\ReactAMQP":"src"}},"require":{"php":">=5.3.0","ext-amqp":"*","evenement\/evenement":"1.0.*","react\/event-loop":"0.3.*"},"uid":477429},"v0.1":{"name":"ovimihai\/react-amqp","description":"AMQP bindings for ReactPHP","keywords":["rabbitmq","AMQP"],"homepage":"","version":"v0.1","version_normalized":"0.1.0.0","license":["MIT"],"authors":[{"name":"Jeremy Cook","email":"jeremycook0@gmail.com"}],"source":{"type":"git","url":"https:\/\/github.com\/ovimihai\/ReactAMQP.git","reference":"663e46753be5ff53a15853ec626c955af953ba95"},"dist":{"type":"zip","url":"https:\/\/api.github.com\/repos\/ovimihai\/ReactAMQP\/zipball\/663e46753be5ff53a15853ec626c955af953ba95","reference":"663e46753be5ff53a15853ec626c955af953ba95","shasum":""},"type":"library","time":"2015-07-29T12:48:08+00:00","autoload":{"psr-0":{"JCook\\ReactAMQP":"src"}},"require":{"php":">=5.3.0","ext-amqp":"*","evenement\/evenement":"1.0.*","react\/event-loop":"0.3.*"},"uid":476399}}}}