{"packages":{"shin1x1\/laravel-force-https-url-scheme":{"dev-master":{"name":"shin1x1\/laravel-force-https-url-scheme","description":"Force https url schema middleware for Laravel 5","keywords":["middleware","laravel"],"homepage":"https:\/\/github.com\/shin1x1\/laravel-force-https-url-scheme","version":"dev-master","version_normalized":"9999999-dev","license":["MIT"],"authors":[{"name":"Masashi Shinbara","email":"shin1x1@gmail.com","homepage":"https:\/\/github.com\/shin1x1"}],"source":{"type":"git","url":"https:\/\/github.com\/shin1x1\/laravel-force-https-url-scheme.git","reference":"992877cc3b9d12bca04e63acce4378bc428489b4"},"dist":{"type":"zip","url":"https:\/\/api.github.com\/repos\/shin1x1\/laravel-force-https-url-scheme\/zipball\/992877cc3b9d12bca04e63acce4378bc428489b4","reference":"992877cc3b9d12bca04e63acce4378bc428489b4","shasum":""},"type":"library","time":"2015-04-16T10:35:40+00:00","autoload":{"psr-4":{"Shin1x1\\ForceHttpsUrlScheme\\":"src","Shin1x1\\ForceHttpsUrlScheme\\Test\\":"tests"}},"require":{"php":">5.4.0","illuminate\/container":"~5.0","illuminate\/http":"~5.0"},"require-dev":{"phpunit\/phpunit":"@stable","mockery\/mockery":"dev-master"},"uid":383190},"v1.0.0":{"name":"shin1x1\/laravel-force-https-url-scheme","description":"Force https url schema middleware for Laravel 5","keywords":["middleware","laravel"],"homepage":"https:\/\/github.com\/shin1x1\/laravel-force-https-url-scheme","version":"v1.0.0","version_normalized":"1.0.0.0","license":["MIT"],"authors":[{"name":"Masashi Shinbara","email":"shin1x1@gmail.com","homepage":"https:\/\/github.com\/shin1x1"}],"source":{"type":"git","url":"https:\/\/github.com\/shin1x1\/laravel-force-https-url-scheme.git","reference":"992877cc3b9d12bca04e63acce4378bc428489b4"},"dist":{"type":"zip","url":"https:\/\/api.github.com\/repos\/shin1x1\/laravel-force-https-url-scheme\/zipball\/992877cc3b9d12bca04e63acce4378bc428489b4","reference":"992877cc3b9d12bca04e63acce4378bc428489b4","shasum":""},"type":"library","time":"2015-04-16T10:35:40+00:00","autoload":{"psr-4":{"Shin1x1\\ForceHttpsUrlScheme\\":"src","Shin1x1\\ForceHttpsUrlScheme\\Test\\":"tests"}},"require":{"php":">5.4.0","illuminate\/container":"~5.0","illuminate\/http":"~5.0"},"require-dev":{"phpunit\/phpunit":"@stable","mockery\/mockery":"dev-master"},"uid":383233}}}}