{"packages":{"filamentv\/yii2-multilang":{"dev-master":{"name":"filamentv\/yii2-multilang","description":"yii2 add multilanguage","keywords":["breadcrumbs","widget","lang","yii2","multilang"],"homepage":"https:\/\/github.com\/FilamentV\/yii2-multilang","version":"dev-master","version_normalized":"9999999-dev","license":["NO"],"authors":[{"name":"FilamentV","email":"vortex.filament@gmail.com"}],"source":{"type":"git","url":"https:\/\/github.com\/FilamentV\/yii2-multilang.git","reference":"1582cdbf44d789c1feff2a6a8e207e6820998c30"},"dist":{"type":"zip","url":"https:\/\/api.github.com\/repos\/FilamentV\/yii2-multilang\/zipball\/1582cdbf44d789c1feff2a6a8e207e6820998c30","reference":"1582cdbf44d789c1feff2a6a8e207e6820998c30","shasum":""},"type":"yii2-component","time":"2015-06-04T12:48:47+00:00","autoload":{"psr-4":{"filamentv\\multilang\\":""}},"require":{"php":">=5.4.0","filamentv\/yii2-app":"dev-master"},"uid":361648}}}}