{"package":{"name":"claromentis\/rssreader","description":"RSS Feed display component","time":"2015-07-02T15:06:39+00:00","maintainers":[{"name":"astax-t"}],"versions":{"dev-master":{"name":"claromentis\/rssreader","description":"RSS Feed display component","keywords":["atom","feed","rss","claromentis"],"homepage":"","version":"dev-master","version_normalized":"9999999-dev","license":["Claromentis License"],"authors":[],"source":{"type":"git","url":"https:\/\/github.com\/Claromentis\/cla-cmp-rss-reader.git","reference":"2de10765d2fd5c5c473125985bedb30e4e1346b2"},"dist":{"type":"zip","url":"https:\/\/api.github.com\/repos\/Claromentis\/cla-cmp-rss-reader\/zipball\/2de10765d2fd5c5c473125985bedb30e4e1346b2","reference":"2de10765d2fd5c5c473125985bedb30e4e1346b2","shasum":""},"type":"claromentis-module-v7","time":"2015-07-02T15:50:22+00:00"},"2.0.0":{"name":"claromentis\/rssreader","description":"RSS Feed display component","keywords":["atom","feed","rss","claromentis"],"homepage":"","version":"2.0.0","version_normalized":"2.0.0.0","license":["Claromentis License"],"authors":[],"source":{"type":"git","url":"https:\/\/github.com\/Claromentis\/cla-cmp-rss-reader.git","reference":"b056f5974df193554fd6a761d167b3298d6392b2"},"dist":{"type":"zip","url":"https:\/\/api.github.com\/repos\/Claromentis\/cla-cmp-rss-reader\/zipball\/b056f5974df193554fd6a761d167b3298d6392b2","reference":"b056f5974df193554fd6a761d167b3298d6392b2","shasum":""},"type":"claromentis-module-v7","time":"2015-07-02T15:13:35+00:00"}},"type":"claromentis-module-v7","repository":"https:\/\/github.com\/Claromentis\/cla-cmp-rss-reader.git","downloads":{"total":9,"monthly":2,"daily":0},"favers":0}}