{"package":{"name":"andig\/php-shunting-yard","description":"Refactored repack of https:\/\/github.com\/andig\/php-shunting-yard","time":"2014-01-06T15:36:15+00:00","maintainers":[{"name":"andig"}],"versions":{"dev-master":{"name":"andig\/php-shunting-yard","description":"Refactored repack of https:\/\/github.com\/andig\/php-shunting-yard","keywords":["math","shunting yard","equation"],"homepage":"https:\/\/github.com\/andig\/php-shunting-yard","version":"dev-master","version_normalized":"9999999-dev","license":["MIT"],"authors":[],"source":{"type":"git","url":"https:\/\/github.com\/andig\/php-shunting-yard.git","reference":"5f59f0cb18a3de6943b71bb712b11d9a535f5eb1"},"dist":{"type":"zip","url":"https:\/\/api.github.com\/repos\/andig\/php-shunting-yard\/zipball\/5f59f0cb18a3de6943b71bb712b11d9a535f5eb1","reference":"5f59f0cb18a3de6943b71bb712b11d9a535f5eb1","shasum":""},"type":"library","time":"2014-12-08T15:25:02+00:00","autoload":{"psr-0":{"RR\\":"src\/"}},"require":{"php":"\u003E=5.3.3"},"require-dev":{"phpunit\/phpunit":"3.7.*"}},"dev-boolean":{"name":"andig\/php-shunting-yard","description":"Refactored repack of https:\/\/github.com\/droptable\/php-shunting-yard","keywords":["math","shunting yard","equation"],"homepage":"https:\/\/github.com\/andig\/php-shunting-yard","version":"dev-boolean","version_normalized":"dev-boolean","license":["MIT"],"authors":[],"source":{"type":"git","url":"https:\/\/github.com\/andig\/php-shunting-yard.git","reference":"6250da5d9927a2ab8c2c6be26565fff0e2b961f9"},"dist":{"type":"zip","url":"https:\/\/api.github.com\/repos\/andig\/php-shunting-yard\/zipball\/6250da5d9927a2ab8c2c6be26565fff0e2b961f9","reference":"6250da5d9927a2ab8c2c6be26565fff0e2b961f9","shasum":""},"type":"library","time":"2014-11-26T11:01:40+00:00","autoload":{"psr-0":{"RR\\":"src\/"}},"require":{"php":"\u003E=5.3.3"},"require-dev":{"phpunit\/phpunit":"3.7.*"}}},"type":"library","repository":"https:\/\/github.com\/andig\/php-shunting-yard.git","downloads":{"total":4715,"monthly":354,"daily":7},"favers":4}}