{"packages":{"breadam\/boom":{"dev-master":{"name":"breadam\/boom","description":"Laravel asset management","keywords":["assets","css","JS","scss","less","coffeescript","laravel","bower","breadam","gulp"],"homepage":"","version":"dev-master","version_normalized":"9999999-dev","license":["MIT"],"authors":[{"name":"breadam","email":"bilgi@breadam.com"}],"source":{"type":"git","url":"https:\/\/github.com\/breadam\/boom.git","reference":"2ad6d47f715d031fc90d327444928a219d91b93c"},"dist":{"type":"zip","url":"https:\/\/api.github.com\/repos\/breadam\/boom\/zipball\/2ad6d47f715d031fc90d327444928a219d91b93c","reference":"2ad6d47f715d031fc90d327444928a219d91b93c","shasum":""},"type":"library","time":"2014-03-02T02:16:58+00:00","autoload":{"psr-0":{"Breadam\\Boom":"src\/"}},"require":{"php":">=5.3.0","illuminate\/support":"4.1.*"},"uid":138895}}}}