{"package":{"name":"phn\/template","description":"","time":"2015-05-13T21:56:26+00:00","maintainers":[{"name":"sukei"}],"versions":{"dev-master":{"name":"phn\/template","description":"","keywords":[],"homepage":"","version":"dev-master","version_normalized":"9999999-dev","license":["MIT"],"authors":[{"name":"Quentin Schuler","email":"qschuler@neosyne.com"}],"source":{"type":"git","url":"https:\/\/github.com\/phn-io\/template.git","reference":"76b57ffca30cf92f6f644eb42cccb4d0a0655a54"},"dist":{"type":"zip","url":"https:\/\/api.github.com\/repos\/phn-io\/template\/zipball\/76b57ffca30cf92f6f644eb42cccb4d0a0655a54","reference":"76b57ffca30cf92f6f644eb42cccb4d0a0655a54","shasum":""},"type":"library","time":"2015-08-14T14:49:31+00:00","autoload":{"psr-0":{"Phn\\Template":"src"}},"require":{"php":"\u003E=5.6","phn\/fragment":"dev-master","phn\/compilation":"dev-master"},"require-dev":{"phpspec\/phpspec":"~2.1","behat\/behat":"~3.0"}}},"type":"library","repository":"https:\/\/github.com\/phn-io\/template","downloads":{"total":36,"monthly":36,"daily":0},"favers":0}}