{"packages":{"jstewmc\/rtf":{"dev-master":{"name":"jstewmc\/rtf","description":"Read and write Rich Text Format (RTF) documents with PHP","keywords":["php","text","parse","format","rtf","render","read","write","rich","lex"],"homepage":"","version":"dev-master","version_normalized":"9999999-dev","license":["MIT"],"authors":[{"name":"Jack Clayton","email":"clayjs0@gmail.com"}],"source":{"type":"git","url":"https:\/\/github.com\/jstewmc\/rtf.git","reference":"db330bce00dd00250c8c9fb9481b54c2a23d5d4b"},"dist":{"type":"zip","url":"https:\/\/api.github.com\/repos\/jstewmc\/rtf\/zipball\/db330bce00dd00250c8c9fb9481b54c2a23d5d4b","reference":"db330bce00dd00250c8c9fb9481b54c2a23d5d4b","shasum":""},"type":"library","time":"2015-08-12T21:35:16+00:00","autoload":{"psr-4":{"Jstewmc\\Rtf\\":"src\/"}},"require":{"jstewmc\/chunker":"0.1.0","jstewmc\/stream":"0.2.1"},"require-dev":{"phpunit\/phpunit":"4.2.*"},"uid":362313},"v0.1.0":{"name":"jstewmc\/rtf","description":"A Rich Text Format (RTF) reader and writer","keywords":["php","text","parse","format","rtf","render","read","write","rich","lex"],"homepage":"","version":"v0.1.0","version_normalized":"0.1.0.0","license":["MIT"],"authors":[{"name":"Jack Clayton","email":"clayjs0@gmail.com"}],"source":{"type":"git","url":"https:\/\/github.com\/jstewmc\/rtf.git","reference":"6b5481564f7990117bbd6abd3b8addbcc67daf70"},"dist":{"type":"zip","url":"https:\/\/api.github.com\/repos\/jstewmc\/rtf\/zipball\/6b5481564f7990117bbd6abd3b8addbcc67daf70","reference":"6b5481564f7990117bbd6abd3b8addbcc67daf70","shasum":""},"type":"library","time":"2015-03-16T17:38:24+00:00","autoload":{"psr-4":{"Jstewmc\\Rtf\\":"src\/"}},"require-dev":{"phpunit\/phpunit":"4.2.*"},"uid":362312},"v0.2.0":{"name":"jstewmc\/rtf","description":"Read and write Rich Text Format (RTF) documents with PHP","keywords":["php","text","parse","format","rtf","render","read","write","rich","lex"],"homepage":"","version":"v0.2.0","version_normalized":"0.2.0.0","license":["MIT"],"authors":[{"name":"Jack Clayton","email":"clayjs0@gmail.com"}],"source":{"type":"git","url":"https:\/\/github.com\/jstewmc\/rtf.git","reference":"feef2dba5a7fb72cd9ce7f76c45d0a6fa8574e4f"},"dist":{"type":"zip","url":"https:\/\/api.github.com\/repos\/jstewmc\/rtf\/zipball\/feef2dba5a7fb72cd9ce7f76c45d0a6fa8574e4f","reference":"feef2dba5a7fb72cd9ce7f76c45d0a6fa8574e4f","shasum":""},"type":"library","time":"2015-07-06T15:12:19+00:00","autoload":{"psr-4":{"Jstewmc\\Rtf\\":"src\/"}},"require":{"jstewmc\/chunker":"0.1.0","jstewmc\/stream":"0.2.1"},"require-dev":{"phpunit\/phpunit":"4.2.*"},"uid":453853},"v0.3.0":{"name":"jstewmc\/rtf","description":"Read and write Rich Text Format (RTF) documents with PHP","keywords":["php","text","parse","format","rtf","render","read","write","rich","lex"],"homepage":"","version":"v0.3.0","version_normalized":"0.3.0.0","license":["MIT"],"authors":[{"name":"Jack Clayton","email":"clayjs0@gmail.com"}],"source":{"type":"git","url":"https:\/\/github.com\/jstewmc\/rtf.git","reference":"49baf5fd14396fdb66bcaa32e6e65365579ba140"},"dist":{"type":"zip","url":"https:\/\/api.github.com\/repos\/jstewmc\/rtf\/zipball\/49baf5fd14396fdb66bcaa32e6e65365579ba140","reference":"49baf5fd14396fdb66bcaa32e6e65365579ba140","shasum":""},"type":"library","time":"2015-07-06T15:42:04+00:00","autoload":{"psr-4":{"Jstewmc\\Rtf\\":"src\/"}},"require":{"jstewmc\/chunker":"0.1.0","jstewmc\/stream":"0.2.1"},"require-dev":{"phpunit\/phpunit":"4.2.*"},"uid":453905},"v0.4.0":{"name":"jstewmc\/rtf","description":"Read and write Rich Text Format (RTF) documents with PHP","keywords":["php","text","parse","format","rtf","render","read","write","rich","lex"],"homepage":"","version":"v0.4.0","version_normalized":"0.4.0.0","license":["MIT"],"authors":[{"name":"Jack Clayton","email":"clayjs0@gmail.com"}],"source":{"type":"git","url":"https:\/\/github.com\/jstewmc\/rtf.git","reference":"d2290ad19a21c4e5acd20f029ab2f8633537ee05"},"dist":{"type":"zip","url":"https:\/\/api.github.com\/repos\/jstewmc\/rtf\/zipball\/d2290ad19a21c4e5acd20f029ab2f8633537ee05","reference":"d2290ad19a21c4e5acd20f029ab2f8633537ee05","shasum":""},"type":"library","time":"2015-08-10T17:58:21+00:00","autoload":{"psr-4":{"Jstewmc\\Rtf\\":"src\/"}},"require":{"jstewmc\/chunker":"0.1.0","jstewmc\/stream":"0.2.1"},"require-dev":{"phpunit\/phpunit":"4.2.*"},"uid":487156},"v0.4.1":{"name":"jstewmc\/rtf","description":"Read and write Rich Text Format (RTF) documents with PHP","keywords":["php","text","parse","format","rtf","render","read","write","rich","lex"],"homepage":"","version":"v0.4.1","version_normalized":"0.4.1.0","license":["MIT"],"authors":[{"name":"Jack Clayton","email":"clayjs0@gmail.com"}],"source":{"type":"git","url":"https:\/\/github.com\/jstewmc\/rtf.git","reference":"66b0dd9ce73d98d10e06106eb8dcea0ba861c9e7"},"dist":{"type":"zip","url":"https:\/\/api.github.com\/repos\/jstewmc\/rtf\/zipball\/66b0dd9ce73d98d10e06106eb8dcea0ba861c9e7","reference":"66b0dd9ce73d98d10e06106eb8dcea0ba861c9e7","shasum":""},"type":"library","time":"2015-08-11T20:52:26+00:00","autoload":{"psr-4":{"Jstewmc\\Rtf\\":"src\/"}},"require":{"jstewmc\/chunker":"0.1.0","jstewmc\/stream":"0.2.1"},"require-dev":{"phpunit\/phpunit":"4.2.*"},"uid":488466},"v0.4.2":{"name":"jstewmc\/rtf","description":"Read and write Rich Text Format (RTF) documents with PHP","keywords":["php","text","parse","format","rtf","render","read","write","rich","lex"],"homepage":"","version":"v0.4.2","version_normalized":"0.4.2.0","license":["MIT"],"authors":[{"name":"Jack Clayton","email":"clayjs0@gmail.com"}],"source":{"type":"git","url":"https:\/\/github.com\/jstewmc\/rtf.git","reference":"86462972e1ff94effe22ec29ff91e4259bb562cd"},"dist":{"type":"zip","url":"https:\/\/api.github.com\/repos\/jstewmc\/rtf\/zipball\/86462972e1ff94effe22ec29ff91e4259bb562cd","reference":"86462972e1ff94effe22ec29ff91e4259bb562cd","shasum":""},"type":"library","time":"2015-08-12T20:08:53+00:00","autoload":{"psr-4":{"Jstewmc\\Rtf\\":"src\/"}},"require":{"jstewmc\/chunker":"0.1.0","jstewmc\/stream":"0.2.1"},"require-dev":{"phpunit\/phpunit":"4.2.*"},"uid":489496}}}}