{"packages":{"gelembjuk\/templating":{"1.0.0":{"name":"gelembjuk\/templating","description":"Common interface for different PHP templating engines like Smarty,Twig. This package allows to switch between engines witout changes in your PHP code","keywords":[],"homepage":"","version":"1.0.0","version_normalized":"1.0.0.0","license":["MIT"],"authors":[{"name":"Roman Gelembjuk","email":"roman@gelembjuk.com"}],"source":{"type":"git","url":"https:\/\/github.com\/Gelembjuk\/templating.git","reference":"d17add80e77a1c10882bbdafed743df133bb8d2e"},"dist":{"type":"zip","url":"https:\/\/api.github.com\/repos\/Gelembjuk\/templating\/zipball\/d17add80e77a1c10882bbdafed743df133bb8d2e","reference":"d17add80e77a1c10882bbdafed743df133bb8d2e","shasum":""},"type":"library","time":"2015-07-28T03:56:10+00:00","autoload":{"psr-0":{"Gelembjuk":"src\/"}},"uid":474526},"dev-master":{"name":"gelembjuk\/templating","description":"Common interface for different PHP templating engines like Smarty,Twig. This package allows to switch between engines witout changes in your PHP code","keywords":[],"homepage":"","version":"dev-master","version_normalized":"9999999-dev","license":["MIT"],"authors":[{"name":"Roman Gelembjuk","email":"roman@gelembjuk.com"}],"source":{"type":"git","url":"https:\/\/github.com\/Gelembjuk\/templating.git","reference":"d17add80e77a1c10882bbdafed743df133bb8d2e"},"dist":{"type":"zip","url":"https:\/\/api.github.com\/repos\/Gelembjuk\/templating\/zipball\/d17add80e77a1c10882bbdafed743df133bb8d2e","reference":"d17add80e77a1c10882bbdafed743df133bb8d2e","shasum":""},"type":"library","time":"2015-07-28T03:56:10+00:00","autoload":{"psr-0":{"Gelembjuk":"src\/"}},"uid":474527}}}}