{"packages":{"mosch\/php-git":{"dev-master":{"name":"mosch\/php-git","description":"A Git wrapper for PHP5.3+","keywords":[],"homepage":"","version":"dev-master","version_normalized":"9999999-dev","license":["MIT"],"authors":[{"name":"Kazuyuki Hayashi","email":"hayashi@valnur.net"},{"name":"Moritz Schwoerer","email":"mr.mosch@gmail.com"}],"source":{"type":"git","url":"https:\/\/github.com\/mosch\/php-git.git","reference":"094a7105329b1a7171e4051c7651cb36930e1a43"},"dist":{"type":"zip","url":"https:\/\/api.github.com\/repos\/mosch\/php-git\/zipball\/094a7105329b1a7171e4051c7651cb36930e1a43","reference":"094a7105329b1a7171e4051c7651cb36930e1a43","shasum":""},"type":"library","time":"2014-11-19T11:35:31+00:00","autoload":{"psr-0":{"":"src"}},"extra":{"branch-alias":{"dev-master":"1.0.x-dev"}},"require":{"php":">=5.3.2","symfony\/process":">=2.3","symfony\/options-resolver":">=2.3"},"require-dev":{"symfony\/filesystem":">=2.3"},"uid":257948},"v0.1.0":{"name":"mosch\/php-git","description":"A Git wrapper for PHP5.3+","keywords":[],"homepage":"","version":"v0.1.0","version_normalized":"0.1.0.0","license":["MIT"],"authors":[{"name":"Kazuyuki Hayashi","email":"hayashi@valnur.net"}],"source":{"type":"git","url":"https:\/\/github.com\/mosch\/php-git.git","reference":"96b3071568e221fc5e2858c44a0c07b75ccbf11a"},"dist":{"type":"zip","url":"https:\/\/api.github.com\/repos\/mosch\/php-git\/zipball\/96b3071568e221fc5e2858c44a0c07b75ccbf11a","reference":"96b3071568e221fc5e2858c44a0c07b75ccbf11a","shasum":""},"type":"library","time":"2014-01-21T15:30:54+00:00","autoload":{"psr-0":{"":"src"}},"extra":{"branch-alias":{"dev-master":"1.0.x-dev"}},"require":{"php":">=5.3.2","symfony\/process":">=2.3","symfony\/options-resolver":">=2.3"},"require-dev":{"symfony\/filesystem":">=2.3"},"uid":257944},"v0.1.1":{"name":"mosch\/php-git","description":"A Git wrapper for PHP5.3+","keywords":[],"homepage":"","version":"v0.1.1","version_normalized":"0.1.1.0","license":["MIT"],"authors":[{"name":"Kazuyuki Hayashi","email":"hayashi@valnur.net"}],"source":{"type":"git","url":"https:\/\/github.com\/mosch\/php-git.git","reference":"4b248eb9366d9329cc53ed7a458795dcc5b0dde7"},"dist":{"type":"zip","url":"https:\/\/api.github.com\/repos\/mosch\/php-git\/zipball\/4b248eb9366d9329cc53ed7a458795dcc5b0dde7","reference":"4b248eb9366d9329cc53ed7a458795dcc5b0dde7","shasum":""},"type":"library","time":"2014-02-01T04:53:46+00:00","autoload":{"psr-0":{"":"src"}},"extra":{"branch-alias":{"dev-master":"1.0.x-dev"}},"require":{"php":">=5.3.2","symfony\/process":">=2.3","symfony\/options-resolver":">=2.3"},"require-dev":{"symfony\/filesystem":">=2.3"},"uid":257945},"v0.1.2":{"name":"mosch\/php-git","description":"A Git wrapper for PHP5.3+","keywords":[],"homepage":"","version":"v0.1.2","version_normalized":"0.1.2.0","license":["MIT"],"authors":[{"name":"Kazuyuki Hayashi","email":"hayashi@valnur.net"}],"source":{"type":"git","url":"https:\/\/github.com\/mosch\/php-git.git","reference":"3c4db987494c38eac300593719a4a7832abddadd"},"dist":{"type":"zip","url":"https:\/\/api.github.com\/repos\/mosch\/php-git\/zipball\/3c4db987494c38eac300593719a4a7832abddadd","reference":"3c4db987494c38eac300593719a4a7832abddadd","shasum":""},"type":"library","time":"2014-02-15T06:18:00+00:00","autoload":{"psr-0":{"":"src"}},"extra":{"branch-alias":{"dev-master":"1.0.x-dev"}},"require":{"php":">=5.3.2","symfony\/process":">=2.3","symfony\/options-resolver":">=2.3"},"require-dev":{"symfony\/filesystem":">=2.3"},"uid":257946},"v0.1.3":{"name":"mosch\/php-git","description":"A Git wrapper for PHP5.3+","keywords":[],"homepage":"","version":"v0.1.3","version_normalized":"0.1.3.0","license":["MIT"],"authors":[{"name":"Kazuyuki Hayashi","email":"hayashi@valnur.net"}],"source":{"type":"git","url":"https:\/\/github.com\/mosch\/php-git.git","reference":"8ef61a79d1b00f5fba9700309890e87808c2134b"},"dist":{"type":"zip","url":"https:\/\/api.github.com\/repos\/mosch\/php-git\/zipball\/8ef61a79d1b00f5fba9700309890e87808c2134b","reference":"8ef61a79d1b00f5fba9700309890e87808c2134b","shasum":""},"type":"library","time":"2014-10-27T13:04:46+00:00","autoload":{"psr-0":{"":"src"}},"extra":{"branch-alias":{"dev-master":"1.0.x-dev"}},"require":{"php":">=5.3.2","symfony\/process":">=2.3","symfony\/options-resolver":">=2.3"},"require-dev":{"symfony\/filesystem":">=2.3"},"uid":257947}}}}