{"packages":{"redgraph\/redgraph":{"dev-master":{"name":"redgraph\/redgraph","description":"A simple graph API for Redis","keywords":["redis","graph"],"homepage":"https:\/\/github.com\/Haensel\/RedGraph","version":"dev-master","version_normalized":"9999999-dev","license":["MIT"],"authors":[{"name":"Johannes 'Haensel' Bauer","email":"johannes@codecrumbs.at","homepage":"http:\/\/codecrumbs.at"}],"source":{"type":"git","url":"https:\/\/github.com\/Haensel\/RedGraph.git","reference":"cf1709615e9847487809cec8e2deb789d3877082"},"dist":{"type":"zip","url":"https:\/\/api.github.com\/repos\/Haensel\/RedGraph\/zipball\/cf1709615e9847487809cec8e2deb789d3877082","reference":"cf1709615e9847487809cec8e2deb789d3877082","shasum":""},"type":"library","time":"2013-03-31T12:43:16+00:00","autoload":{"psr-0":{"RedGraph":"src"}},"require":{"php":">=5.4.0","pimple\/pimple":"1.0.2","predis\/predis":"*"},"require-dev":{"phpunit\/phpunit":"3.7.*"},"uid":42156}}}}