{"packages":{"consultnn\/yii2-select2":{"dev-master":{"name":"consultnn\/yii2-select2","description":"Yii2 widget wrapper for jquery select2 plugin v4.*","keywords":[],"homepage":"","version":"dev-master","version_normalized":"9999999-dev","license":["MIT"],"authors":[{"name":"sega","email":"i.i.iahid@gmail.com"},{"name":"sokrat","email":"sergey.sipatov@gmail.com"}],"source":{"type":"git","url":"https:\/\/github.com\/consultnn\/yii2-select2.git","reference":"c8b3a32cc14270ecb49ff69aad4705bdfff2dc02"},"dist":{"type":"zip","url":"https:\/\/api.github.com\/repos\/consultnn\/yii2-select2\/zipball\/c8b3a32cc14270ecb49ff69aad4705bdfff2dc02","reference":"c8b3a32cc14270ecb49ff69aad4705bdfff2dc02","shasum":""},"type":"library","time":"2015-08-24T14:15:59+00:00","autoload":{"psr-4":{"consultnn\\select2\\":"."}},"require":{"php":">=5.4.0","bower-asset\/select2":"4.*","yiisoft\/yii2":"2.0.*"},"uid":408897},"v1.0":{"name":"consultnn\/yii2-select2","description":"Yii2 widget wrapper for jquery select2 plugin v4.*","keywords":[],"homepage":"","version":"v1.0","version_normalized":"1.0.0.0","license":["MIT"],"authors":[{"name":"sega","email":"i.i.iahid@gmail.com"},{"name":"sokrat","email":"sergey.sipatov@gmail.com"}],"source":{"type":"git","url":"https:\/\/github.com\/consultnn\/yii2-select2.git","reference":"59754d403e966adae9853be5ecfd90ed7e08fb2d"},"dist":{"type":"zip","url":"https:\/\/api.github.com\/repos\/consultnn\/yii2-select2\/zipball\/59754d403e966adae9853be5ecfd90ed7e08fb2d","reference":"59754d403e966adae9853be5ecfd90ed7e08fb2d","shasum":""},"type":"library","time":"2015-08-07T12:05:54+00:00","autoload":{"psr-4":{"consultnn\\select2\\":"."}},"require":{"php":">=5.4.0","yiisoft\/yii2":"2.0.*","bower-asset\/select2":"4.*"},"uid":484648}}}}